{
    "name": "power_shot",
    "author": "Your name",
    "description": "description",
    "emote":{
        "isLoop": "true",
        "returnTick": 12,
        "beginTick":0,
        "endTick":20,
        "stopTick":21,
        "degrees":false,
        "moves":[
            
            {
                "tick":12,
                "easing": "EASEINOUTQUAD",
                "turn": 0,
                "torso":{
                    "yaw":-0.13194206357002258
                }
            },
            {
                "tick":20,
                "easing": "EASEINOUTQUAD",
                "turn": 0,
                "torso":{
                    "yaw":-0.13194206357002258
                }
            },
            {
                "tick":12,
                "easing": "EASEINOUTQUAD",
                "turn": 0,
                "torso":{
                    "roll":0.04778359457850456
                }
            },
            {
                "tick":20,
                "easing": "EASEINOUTQUAD",
                "turn": 0,
                "torso":{
                    "roll":0.04778359457850456
                }
            },
            {
                "tick":12,
                "easing": "EASEINOUTQUAD",
                "turn": 0,
                "torso":{
                    "pitch":-0.015223516151309013
                }
            },
            {
                "tick":20,
                "easing": "EASEINOUTQUAD",
                "turn": 0,
                "torso":{
                    "pitch":-0.015223516151309013
                }
            },
            {
                "tick":12,
                "easing": "EASEINOUTQUAD",
                "turn": 0,
                "torso":{
                    "y":0.051361773163080215
                }
            },
            {
                "tick":20,
                "easing": "EASEINOUTQUAD",
                "turn": 0,
                "torso":{
                    "y":0.051361773163080215
                }
            },
            {
                "tick":12,
                "easing": "EASEINOUTQUAD",
                "turn": 0,
                "torso":{
                    "x":0.0
                }
            },
            {
                "tick":20,
                "easing": "EASEINOUTQUAD",
                "turn": 0,
                "torso":{
                    "x":0.0
                }
            },
            {
                "tick":12,
                "easing": "EASEINOUTQUAD",
                "turn": 0,
                "torso":{
                    "z":-0.0
                }
            },
            {
                "tick":20,
                "easing": "EASEINOUTQUAD",
                "turn": 0,
                "torso":{
                    "z":-0.0
                }
            },
            {
                "tick":12,
                "easing": "EASEINOUTQUAD",
                "turn": 0,
                "rightArm":{
                    "yaw":0.25431907176971436
                }
            },
            {
                "tick":20,
                "easing": "EASEINOUTQUAD",
                "turn": 0,
                "rightArm":{
                    "yaw":0.25431907176971436
                }
            },
            {
                "tick":12,
                "easing": "EASEINOUTQUAD",
                "turn": 0,
                "rightArm":{
                    "roll":-0.0
                }
            },
            {
                "tick":20,
                "easing": "EASEINOUTQUAD",
                "turn": 0,
                "rightArm":{
                    "roll":-0.0
                }
            },
            {
                "tick":12,
                "easing": "EASEINOUTQUAD",
                "turn": 0,
                "rightArm":{
                    "y":2.0
                }
            },
            {
                "tick":20,
                "easing": "EASEINOUTQUAD",
                "turn": 0,
                "rightArm":{
                    "y":2.0
                }
            },
            {
                "tick":12,
                "easing": "EASEINOUTQUAD",
                "turn": 0,
                "rightArm":{
                    "z":-0.0
                }
            },
            {
                "tick":20,
                "easing": "EASEINOUTQUAD",
                "turn": 0,
                "rightArm":{
                    "z":-0.0
                }
            },
            {
                "tick":12,
                "easing": "EASEINOUTQUAD",
                "turn": 0,
                "rightArm":{
                    "x":-5.0
                }
            },
            {
                "tick":20,
                "easing": "EASEINOUTQUAD",
                "turn": 0,
                "rightArm":{
                    "x":-5.0
                }
            },
            {
                "tick":12,
                "easing": "EASEINOUTQUAD",
                "turn": 0,
                "rightArm":{
                    "pitch":-2.4511170387268066
                }
            },
            {
                "tick":20,
                "easing": "EASEINOUTQUAD",
                "turn": 0,
                "rightArm":{
                    "pitch":-2.4511170387268066
                }
            },
            {
                "tick":12,
                "easing": "EASEINOUTQUAD",
                "turn": 0,
                "leftArm":{
                    "roll":-1.4168963432312012
                }
            },
            {
                "tick":20,
                "easing": "EASEINOUTQUAD",
                "turn": 0,
                "leftArm":{
                    "roll":-1.4168963432312012
                }
            },
            {
                "tick":12,
                "easing": "EASEINOUTQUAD",
                "turn": 0,
                "leftArm":{
                    "yaw":0.6871852278709412
                }
            },
            {
                "tick":20,
                "easing": "EASEINOUTQUAD",
                "turn": 0,
                "leftArm":{
                    "yaw":0.6871852278709412
                }
            },
            {
                "tick":12,
                "easing": "EASEINOUTQUAD",
                "turn": 0,
                "leftArm":{
                    "pitch":-1.1845778226852417
                }
            },
            {
                "tick":20,
                "easing": "EASEINOUTQUAD",
                "turn": 0,
                "leftArm":{
                    "pitch":-1.1845778226852417
                }
            },
            {
                "tick":12,
                "easing": "EASEINOUTQUAD",
                "turn": 0,
                "leftArm":{
                    "y":2.0
                }
            },
            {
                "tick":20,
                "easing": "EASEINOUTQUAD",
                "turn": 0,
                "leftArm":{
                    "y":2.0
                }
            },
            {
                "tick":12,
                "easing": "EASEINOUTQUAD",
                "turn": 0,
                "leftArm":{
                    "z":-0.0
                }
            },
            {
                "tick":20,
                "easing": "EASEINOUTQUAD",
                "turn": 0,
                "leftArm":{
                    "z":-0.0
                }
            },
            {
                "tick":12,
                "easing": "EASEINOUTQUAD",
                "turn": 0,
                "leftArm":{
                    "x":5.0
                }
            },
            {
                "tick":20,
                "easing": "EASEINOUTQUAD",
                "turn": 0,
                "leftArm":{
                    "x":5.0
                }
            },
            {
                "tick":12,
                "easing": "EASEINOUTQUAD",
                "turn": 0,
                "rightLeg":{
                    "yaw":0.08812224864959717
                }
            },
            {
                "tick":20,
                "easing": "EASEINOUTQUAD",
                "turn": 0,
                "rightLeg":{
                    "yaw":0.08812224864959717
                }
            },
            {
                "tick":12,
                "easing": "EASEINOUTQUAD",
                "turn": 0,
                "rightLeg":{
                    "roll":0.0036393292248249054
                }
            },
            {
                "tick":20,
                "easing": "EASEINOUTQUAD",
                "turn": 0,
                "rightLeg":{
                    "roll":0.0036393292248249054
                }
            },
            {
                "tick":12,
                "easing": "EASEINOUTQUAD",
                "turn": 0,
                "rightLeg":{
                    "pitch":-0.17526474595069885
                }
            },
            {
                "tick":20,
                "easing": "EASEINOUTQUAD",
                "turn": 0,
                "rightLeg":{
                    "pitch":-0.17526474595069885
                }
            },
            {
                "tick":12,
                "easing": "EASEINOUTQUAD",
                "turn": 0,
                "rightLeg":{
                    "x":-1.9
                }
            },
            {
                "tick":20,
                "easing": "EASEINOUTQUAD",
                "turn": 0,
                "rightLeg":{
                    "x":-1.9
                }
            },
            {
                "tick":12,
                "easing": "EASEINOUTQUAD",
                "turn": 0,
                "rightLeg":{
                    "y":12.0
                }
            },
            {
                "tick":20,
                "easing": "EASEINOUTQUAD",
                "turn": 0,
                "rightLeg":{
                    "y":12.0
                }
            },
            {
                "tick":12,
                "easing": "EASEINOUTQUAD",
                "turn": 0,
                "rightLeg":{
                    "z":0.1
                }
            },
            {
                "tick":20,
                "easing": "EASEINOUTQUAD",
                "turn": 0,
                "rightLeg":{
                    "z":0.1
                }
            },
            {
                "tick":12,
                "easing": "EASEINOUTQUAD",
                "turn": 0,
                "leftLeg":{
                    "yaw":-0.0
                }
            },
            {
                "tick":20,
                "easing": "EASEINOUTQUAD",
                "turn": 0,
                "leftLeg":{
                    "yaw":-0.0
                }
            },
            {
                "tick":12,
                "easing": "EASEINOUTQUAD",
                "turn": 0,
                "leftLeg":{
                    "roll":-0.06700029969215393
                }
            },
            {
                "tick":20,
                "easing": "EASEINOUTQUAD",
                "turn": 0,
                "leftLeg":{
                    "roll":-0.06700029969215393
                }
            },
            {
                "tick":12,
                "easing": "EASEINOUTQUAD",
                "turn": 0,
                "leftLeg":{
                    "pitch":0.0
                }
            },
            {
                "tick":20,
                "easing": "EASEINOUTQUAD",
                "turn": 0,
                "leftLeg":{
                    "pitch":0.0
                }
            },
            {
                "tick":12,
                "easing": "EASEINOUTQUAD",
                "turn": 0,
                "leftLeg":{
                    "y":12.0
                }
            },
            {
                "tick":20,
                "easing": "EASEINOUTQUAD",
                "turn": 0,
                "leftLeg":{
                    "y":12.0
                }
            },
            {
                "tick":12,
                "easing": "EASEINOUTQUAD",
                "turn": 0,
                "leftLeg":{
                    "z":-0.1
                }
            },
            {
                "tick":20,
                "easing": "EASEINOUTQUAD",
                "turn": 0,
                "leftLeg":{
                    "z":-0.1
                }
            },
            {
                "tick":12,
                "easing": "EASEINOUTQUAD",
                "turn": 0,
                "leftLeg":{
                    "x":1.9
                }
            },
            {
                "tick":20,
                "easing": "EASEINOUTQUAD",
                "turn": 0,
                "leftLeg":{
                    "x":1.9
                }
            }
        ]
    }
}